iragnsep/SEDanalysis.py
iragnsep/__init__.py
iragnsep/classes.py
iragnsep/func.py
iragnsep/iragnsep_templ.csv
iragnsep/run_all.py
iragnsep/toolplot.py
iragnsep/ExtCurves/CT06_extCurve.csv
iragnsep/ExtCurves/Min+07.csv
iragnsep/ExtCurves/PAHfit_extCurve.csv
iragnsep/ExtCurves/PAHfit_extCurve_updated.csv
iragnsep/ExtCurves/iragnsep_extCurve.csv
iragnsep/Filters/IRAC1Filter.csv
iragnsep/Filters/IRAC2Filter.csv
iragnsep/Filters/IRAC3Filter.csv
iragnsep/Filters/IRAC4Filter.csv
iragnsep/Filters/IRAS100Filter.csv
iragnsep/Filters/IRAS12Filter.csv
iragnsep/Filters/IRAS25Filter.csv
iragnsep/Filters/IRAS60Filter.csv
iragnsep/Filters/ISOPHTC100Filter.csv
iragnsep/Filters/MIPS160Filter.csv
iragnsep/Filters/MIPS24Filter.csv
iragnsep/Filters/MIPS70Filter.csv
iragnsep/Filters/PACS100Filter.csv
iragnsep/Filters/PACS160Filter.csv
iragnsep/Filters/PACS70Filter.csv
iragnsep/Filters/SPIRE250psFilter.csv
iragnsep/Filters/SPIRE350psFilter.csv
iragnsep/Filters/SPIRE500psFilter.csv
iragnsep/Filters/Spitz_i4.csv
iragnsep/Filters/WISE_W1Filter.csv
iragnsep/Filters/WISE_W2Filter.csv
iragnsep/Filters/WISE_W3Filter.csv
iragnsep/Filters/WISE_W4Filter.csv
iragnsep-7.3.2.dist-info/.DS_Store
iragnsep-7.3.2.dist-info/LICENSE
iragnsep-7.3.2.dist-info/METADATA
iragnsep-7.3.2.dist-info/WHEEL
iragnsep-7.3.2.dist-info/top_level.txt
iragnsep-7.3.2.dist-info/RECORD
