Metadata-Version: 2.1
Name: iragnsep
Version: 7.3.2
Summary: Fits of IR SEDs including AGN contribution.
Home-page: https://tinyurl.com/y9phjhxy
Author: Emmanuel Bernhard
Author-email: manu.p.bernhard@gmail.com
License: UNKNOWN
Platform: UNKNOWN
Classifier: Programming Language :: Python :: 3
Classifier: License :: OSI Approved :: MIT License
Classifier: Operating System :: OS Independent
Requires-Python: >=3.7
Requires-Dist: numpy (>=1.20.3)
Requires-Dist: matplotlib (>=3.4.2)
Requires-Dist: astropy (>=4.2.1)
Requires-Dist: scipy (>=1.6.3)
Requires-Dist: pandas (>=1.2.4)
Requires-Dist: emcee (>=3.0.2)
Requires-Dist: numba (>=0.53.1)
Requires-Dist: tqdm (>=4.61.0)
